pybehave/__init__.py
pybehave/configuration/default-config.json
pybehave/drivers/README.md
pybehave/drivers/chromedriver
pybehave/drivers/msedgedriver
pybehave/features/__init__.py
pybehave/features/environment.py
pybehave/features/example/api_request.feature
pybehave/features/example/database_connection.feature
pybehave/features/example/login.feature
pybehave/features/steps/__init__.py
pybehave/features/steps/all_steps.py
pybehave/features/steps/example/api_steps.py
pybehave/features/steps/example/database_steps.py
pybehave/features/steps/example/login_steps.py
pybehave/support/__init__.py
pybehave/support/config.py
pybehave/support/settings.py
pybehave/support/test-settings.json
pybehave/support/apiclientactions/__init__.py
pybehave/support/apiclientactions/apiclient.py
pybehave/support/builders/example/examplerequestbuilder.py
pybehave/support/builders/templates/example.xml
pybehave/support/core/__init__.py
pybehave/support/core/elementaction.py
pybehave/support/facades/example/apiaction.py
pybehave/support/facades/example/databaseaction.py
pybehave/support/facades/example/loginaction.py
pybehave/support/locators/__init__.py
pybehave/support/locators/general.py
pybehave/support/locators/locator.py
pybehave/support/locators/locatortype.py
pybehave/support/locators/example/loginlocator.py
pybehave/support/pageactions/__init__.py
pybehave/support/pageactions/actionenum.py
pybehave/support/pageactions/basepage.py
pybehave/support/pageactions/commonactions.py
pybehave/support/pageactions/example/loginpage.py
pybehave/utils/__init__.py
pybehave/utils/assertutils.py
pybehave/utils/baseconfigreader.py
pybehave/utils/configfilereader.py
pybehave/utils/keyvaultreader.py
pybehave/utils/testdatahelper.py
pybehave/utils/utils.py
pybehave_selenium_test_framework-1.0.5.dist-info/METADATA
pybehave_selenium_test_framework-1.0.5.dist-info/WHEEL
pybehave_selenium_test_framework-1.0.5.dist-info/licenses/LICENSE.txt
pybehave_selenium_test_framework-1.0.5.dist-info/RECORD
