Metadata-Version: 2.4
Name: pybehave-selenium-test-framework
Version: 1.0.5
Summary: A powerful test automation framework designed to provide a comprehensive solution for testing user interfaces and APIs
Project-URL: Homepage, https://github.com/argodevops/pytest-behave
Project-URL: Issues, https://github.com/argodevops/pytest-behave/issues
Author-email: Argo DevOps <enquiry@argodevops.co.uk>
License:                                  Apache License
License-File: LICENSE.txt
Keywords: behave,selenium
Classifier: License :: OSI Approved :: Apache Software License
Classifier: Operating System :: OS Independent
Classifier: Programming Language :: Python :: 3.9
Classifier: Programming Language :: Python :: 3.10
Classifier: Programming Language :: Python :: 3.11
Requires-Python: >=3.9
Requires-Dist: allure-behave>=2.13.2
Requires-Dist: allure-python-commons>=2.13.2
Requires-Dist: art>=6.1
Requires-Dist: attrs>=23.1.0
Requires-Dist: azure-cli>=2.53.1
Requires-Dist: azure-identity>=1.16.1
Requires-Dist: azure-keyvault-secrets>=4.7.0
Requires-Dist: azure-keyvault>=4.2.0
Requires-Dist: behave>=1.2.6
Requires-Dist: behavex>=2.0.1
Requires-Dist: black>=24.3.0
Requires-Dist: ddt>=1.6.0
Requires-Dist: elementpath>=4.1.4
Requires-Dist: faker>=19.1.0
Requires-Dist: iniconfig>=2.0.0
Requires-Dist: jinja2>=3.1.5
Requires-Dist: numpy>=1.22.2
Requires-Dist: packaging>=23.1
Requires-Dist: panda>=0.3.1
Requires-Dist: paramiko>=3.4.0
Requires-Dist: parse-type>=0.6.2
Requires-Dist: parse>=1.19.1
Requires-Dist: pdfminer-six>=20240706
Requires-Dist: pillow>=10.3.0
Requires-Dist: pluggy>=1.2.0
Requires-Dist: pre-commit>=3.3.3
Requires-Dist: py>=1.11.0
Requires-Dist: pyautogui>=0.9.54
Requires-Dist: pygount>=1.2.4
Requires-Dist: pyhamcrest>=2.1.0
Requires-Dist: pylint>=2.17.4
Requires-Dist: pyodbc>=4.0.39
Requires-Dist: pyparsing>=3.1.0
Requires-Dist: pytest>=7.4.0
Requires-Dist: pyupgrade>=3.15.0
Requires-Dist: requests>=2.32.0
Requires-Dist: ruff>=0.2.1
Requires-Dist: selenium-screenshot>=2.1.0
Requires-Dist: selenium>=4.15.2
Requires-Dist: setuptools>=65.5.1
Requires-Dist: shortuuid>=1.0.11
Requires-Dist: six>=1.16.0
Requires-Dist: testresources>=2.0.1
Requires-Dist: toml>=0.10.2
Requires-Dist: typing-extensions>=4.7.1
Requires-Dist: urllib3>=2.2.2
Requires-Dist: wily>=1.24.2
Requires-Dist: xmltodict>=0.13.0
